<?xml version="1.0" encoding="UTF-8"?>
<!DOCTYPE POWERMART SYSTEM "powrmart.dtd">
<POWERMART CREATION_DATE="03/23/2026 10:00:00" REPOSITORY_VERSION="186.90">
<REPOSITORY NAME="PROD_REPO" VERSION="186" DATABASETYPE="Oracle">
<FOLDER NAME="SALES_ETL" GROUP="" OWNER="admin" SHARED="NOTSHARED" DESCRIPTION="Sales ETL Mappings" PERMISSIONS="rwx------">

<!-- ============================================================ -->
<!-- MAPPING: M_LOAD_CUSTOMERS (Simple — SQ → EXP → FIL → TGT)   -->
<!-- ============================================================ -->

<!-- Source Table Definition -->
<SOURCE BUSINESSNAME="" DATABASETYPE="Oracle" DBDNAME="ORACLE_PROD" DESCRIPTION="Customer master table" NAME="CUSTOMERS" OBJECTVERSION="1" OWNERNAME="SALES" VERSIONNUMBER="1">
  <SOURCEFIELD BUSINESSNAME="" DATATYPE="number" DESCRIPTION="Primary key" FIELDNUMBER="1" FIELDPROPERTY="0" FIELDTYPE="ELEMITEM" HIDDEN="NO" KEYTYPE="PRIMARY KEY" LENGTH="0" LEVEL="0" NAME="CUSTOMER_ID" NULLABLE="NOTNULL" OCCURS="0" OFFSET="0" PHYSICALLENGTH="10" PHYSICALOFFSET="0" PICTURETEXT="" PRECISION="10" SCALE="0" USAGE_FLAGS=""/>
  <SOURCEFIELD BUSINESSNAME="" DATATYPE="varchar2" DESCRIPTION="First name" FIELDNUMBER="2" FIELDPROPERTY="0" FIELDTYPE="ELEMITEM" HIDDEN="NO" KEYTYPE="NOT A KEY" LENGTH="100" LEVEL="0" NAME="FIRST_NAME" NULLABLE="NULL" OCCURS="0" OFFSET="0" PHYSICALLENGTH="100" PHYSICALOFFSET="0" PICTURETEXT="" PRECISION="100" SCALE="0" USAGE_FLAGS=""/>
  <SOURCEFIELD BUSINESSNAME="" DATATYPE="varchar2" DESCRIPTION="Last name" FIELDNUMBER="3" FIELDPROPERTY="0" FIELDTYPE="ELEMITEM" HIDDEN="NO" KEYTYPE="NOT A KEY" LENGTH="100" LEVEL="0" NAME="LAST_NAME" NULLABLE="NULL" OCCURS="0" OFFSET="0" PHYSICALLENGTH="100" PHYSICALOFFSET="0" PICTURETEXT="" PRECISION="100" SCALE="0" USAGE_FLAGS=""/>
  <SOURCEFIELD BUSINESSNAME="" DATATYPE="varchar2" DESCRIPTION="Email address" FIELDNUMBER="4" FIELDPROPERTY="0" FIELDTYPE="ELEMITEM" HIDDEN="NO" KEYTYPE="NOT A KEY" LENGTH="250" LEVEL="0" NAME="EMAIL" NULLABLE="NULL" OCCURS="0" OFFSET="0" PHYSICALLENGTH="250" PHYSICALOFFSET="0" PICTURETEXT="" PRECISION="250" SCALE="0" USAGE_FLAGS=""/>
  <SOURCEFIELD BUSINESSNAME="" DATATYPE="varchar2" DESCRIPTION="Customer status" FIELDNUMBER="5" FIELDPROPERTY="0" FIELDTYPE="ELEMITEM" HIDDEN="NO" KEYTYPE="NOT A KEY" LENGTH="20" LEVEL="0" NAME="STATUS" NULLABLE="NULL" OCCURS="0" OFFSET="0" PHYSICALLENGTH="20" PHYSICALOFFSET="0" PICTURETEXT="" PRECISION="20" SCALE="0" USAGE_FLAGS=""/>
  <SOURCEFIELD BUSINESSNAME="" DATATYPE="date" DESCRIPTION="Registration date" FIELDNUMBER="6" FIELDPROPERTY="0" FIELDTYPE="ELEMITEM" HIDDEN="NO" KEYTYPE="NOT A KEY" LENGTH="19" LEVEL="0" NAME="REGISTRATION_DATE" NULLABLE="NULL" OCCURS="0" OFFSET="0" PHYSICALLENGTH="19" PHYSICALOFFSET="0" PICTURETEXT="" PRECISION="19" SCALE="0" USAGE_FLAGS=""/>
  <SOURCEFIELD BUSINESSNAME="" DATATYPE="number" DESCRIPTION="Credit limit" FIELDNUMBER="7" FIELDPROPERTY="0" FIELDTYPE="ELEMITEM" HIDDEN="NO" KEYTYPE="NOT A KEY" LENGTH="0" LEVEL="0" NAME="CREDIT_LIMIT" NULLABLE="NULL" OCCURS="0" OFFSET="0" PHYSICALLENGTH="15" PHYSICALOFFSET="0" PICTURETEXT="" PRECISION="15" SCALE="2" USAGE_FLAGS=""/>
  <SOURCEFIELD BUSINESSNAME="" DATATYPE="varchar2" DESCRIPTION="Country code" FIELDNUMBER="8" FIELDPROPERTY="0" FIELDTYPE="ELEMITEM" HIDDEN="NO" KEYTYPE="NOT A KEY" LENGTH="3" LEVEL="0" NAME="COUNTRY_CODE" NULLABLE="NULL" OCCURS="0" OFFSET="0" PHYSICALLENGTH="3" PHYSICALOFFSET="0" PICTURETEXT="" PRECISION="3" SCALE="0" USAGE_FLAGS=""/>
</SOURCE>

<!-- Target Table Definition -->
<TARGET BUSINESSNAME="" CONSTRAINT="" DATABASETYPE="Oracle" DESCRIPTION="Silver layer customer dimension" NAME="DIM_CUSTOMER" OBJECTVERSION="1" TABLESPACE="" VERSIONNUMBER="1">
  <TARGETFIELD BUSINESSNAME="" DATATYPE="number" DESCRIPTION="Surrogate key" FIELDNUMBER="1" KEYTYPE="PRIMARY KEY" NAME="CUSTOMER_SK" NULLABLE="NOTNULL" PICTURETEXT="" PRECISION="10" SCALE="0"/>
  <TARGETFIELD BUSINESSNAME="" DATATYPE="number" DESCRIPTION="Business key" FIELDNUMBER="2" KEYTYPE="NOT A KEY" NAME="CUSTOMER_ID" NULLABLE="NOTNULL" PICTURETEXT="" PRECISION="10" SCALE="0"/>
  <TARGETFIELD BUSINESSNAME="" DATATYPE="varchar2" DESCRIPTION="Full name" FIELDNUMBER="3" KEYTYPE="NOT A KEY" NAME="FULL_NAME" NULLABLE="NULL" PICTURETEXT="" PRECISION="201" SCALE="0"/>
  <TARGETFIELD BUSINESSNAME="" DATATYPE="varchar2" DESCRIPTION="Email" FIELDNUMBER="4" KEYTYPE="NOT A KEY" NAME="EMAIL" NULLABLE="NULL" PICTURETEXT="" PRECISION="250" SCALE="0"/>
  <TARGETFIELD BUSINESSNAME="" DATATYPE="varchar2" DESCRIPTION="Status label" FIELDNUMBER="5" KEYTYPE="NOT A KEY" NAME="STATUS_LABEL" NULLABLE="NULL" PICTURETEXT="" PRECISION="50" SCALE="0"/>
  <TARGETFIELD BUSINESSNAME="" DATATYPE="number" DESCRIPTION="Credit limit" FIELDNUMBER="6" KEYTYPE="NOT A KEY" NAME="CREDIT_LIMIT" NULLABLE="NULL" PICTURETEXT="" PRECISION="15" SCALE="2"/>
  <TARGETFIELD BUSINESSNAME="" DATATYPE="varchar2" DESCRIPTION="Country code" FIELDNUMBER="7" KEYTYPE="NOT A KEY" NAME="COUNTRY_CODE" NULLABLE="NULL" PICTURETEXT="" PRECISION="3" SCALE="0"/>
  <TARGETFIELD BUSINESSNAME="" DATATYPE="date" DESCRIPTION="ETL load timestamp" FIELDNUMBER="8" KEYTYPE="NOT A KEY" NAME="ETL_LOAD_DATE" NULLABLE="NULL" PICTURETEXT="" PRECISION="19" SCALE="0"/>
</TARGET>

<!-- Mapping Definition -->
<MAPPING DESCRIPTION="Load customers from Oracle to Silver DIM_CUSTOMER" ISVALID="YES" NAME="M_LOAD_CUSTOMERS" OBJECTVERSION="1" VERSIONNUMBER="1">

  <!-- Source Qualifier -->
  <TRANSFORMATION DESCRIPTION="Read from CUSTOMERS" NAME="SQ_CUSTOMERS" OBJECTVERSION="1" REUSABLE="NO" TYPE="Source Qualifier" VERSIONNUMBER="1">
    <TRANSFORMFIELD DATATYPE="number" DEFAULTVALUE="" DESCRIPTION="" NAME="CUSTOMER_ID" PICTURETEXT="" PORTTYPE="INPUT/OUTPUT" PRECISION="10" SCALE="0"/>
    <TRANSFORMFIELD DATATYPE="string" DEFAULTVALUE="" DESCRIPTION="" NAME="FIRST_NAME" PICTURETEXT="" PORTTYPE="INPUT/OUTPUT" PRECISION="100" SCALE="0"/>
    <TRANSFORMFIELD DATATYPE="string" DEFAULTVALUE="" DESCRIPTION="" NAME="LAST_NAME" PICTURETEXT="" PORTTYPE="INPUT/OUTPUT" PRECISION="100" SCALE="0"/>
    <TRANSFORMFIELD DATATYPE="string" DEFAULTVALUE="" DESCRIPTION="" NAME="EMAIL" PICTURETEXT="" PORTTYPE="INPUT/OUTPUT" PRECISION="250" SCALE="0"/>
    <TRANSFORMFIELD DATATYPE="string" DEFAULTVALUE="" DESCRIPTION="" NAME="STATUS" PICTURETEXT="" PORTTYPE="INPUT/OUTPUT" PRECISION="20" SCALE="0"/>
    <TRANSFORMFIELD DATATYPE="date/time" DEFAULTVALUE="" DESCRIPTION="" NAME="REGISTRATION_DATE" PICTURETEXT="" PORTTYPE="INPUT/OUTPUT" PRECISION="19" SCALE="0"/>
    <TRANSFORMFIELD DATATYPE="number" DEFAULTVALUE="" DESCRIPTION="" NAME="CREDIT_LIMIT" PICTURETEXT="" PORTTYPE="INPUT/OUTPUT" PRECISION="15" SCALE="2"/>
    <TRANSFORMFIELD DATATYPE="string" DEFAULTVALUE="" DESCRIPTION="" NAME="COUNTRY_CODE" PICTURETEXT="" PORTTYPE="INPUT/OUTPUT" PRECISION="3" SCALE="0"/>
    <TABLEATTRIBUTE NAME="Sql Query" VALUE=""/>
    <TABLEATTRIBUTE NAME="User Defined Join" VALUE=""/>
    <TABLEATTRIBUTE NAME="Source Filter" VALUE=""/>
    <TABLEATTRIBUTE NAME="Number Of Sorted Ports" VALUE="0"/>
    <TABLEATTRIBUTE NAME="Tracing Level" VALUE="Normal"/>
  </TRANSFORMATION>

  <!-- Expression: Derive full_name and status_label -->
  <TRANSFORMATION DESCRIPTION="Derive computed columns" NAME="EXP_DERIVE_FIELDS" OBJECTVERSION="1" REUSABLE="NO" TYPE="Expression" VERSIONNUMBER="1">
    <TRANSFORMFIELD DATATYPE="number" DEFAULTVALUE="" DESCRIPTION="" EXPRESSION="CUSTOMER_ID" EXPRESSIONTYPE="GENERAL" NAME="CUSTOMER_ID" PICTURETEXT="" PORTTYPE="INPUT/OUTPUT" PRECISION="10" SCALE="0"/>
    <TRANSFORMFIELD DATATYPE="string" DEFAULTVALUE="" DESCRIPTION="" EXPRESSION="FIRST_NAME" EXPRESSIONTYPE="GENERAL" NAME="FIRST_NAME" PICTURETEXT="" PORTTYPE="INPUT" PRECISION="100" SCALE="0"/>
    <TRANSFORMFIELD DATATYPE="string" DEFAULTVALUE="" DESCRIPTION="" EXPRESSION="LAST_NAME" EXPRESSIONTYPE="GENERAL" NAME="LAST_NAME" PICTURETEXT="" PORTTYPE="INPUT" PRECISION="100" SCALE="0"/>
    <TRANSFORMFIELD DATATYPE="string" DEFAULTVALUE="" DESCRIPTION="" EXPRESSION="FIRST_NAME || ' ' || LAST_NAME" EXPRESSIONTYPE="GENERAL" NAME="FULL_NAME" PICTURETEXT="" PORTTYPE="OUTPUT" PRECISION="201" SCALE="0"/>
    <TRANSFORMFIELD DATATYPE="string" DEFAULTVALUE="" DESCRIPTION="" EXPRESSION="EMAIL" EXPRESSIONTYPE="GENERAL" NAME="EMAIL" PICTURETEXT="" PORTTYPE="INPUT/OUTPUT" PRECISION="250" SCALE="0"/>
    <TRANSFORMFIELD DATATYPE="string" DEFAULTVALUE="" DESCRIPTION="" EXPRESSION="STATUS" EXPRESSIONTYPE="GENERAL" NAME="STATUS" PICTURETEXT="" PORTTYPE="INPUT" PRECISION="20" SCALE="0"/>
    <TRANSFORMFIELD DATATYPE="string" DEFAULTVALUE="" DESCRIPTION="" EXPRESSION="IIF(STATUS = 'A', 'Active', IIF(STATUS = 'I', 'Inactive', IIF(STATUS = 'S', 'Suspended', 'Unknown')))" EXPRESSIONTYPE="GENERAL" NAME="STATUS_LABEL" PICTURETEXT="" PORTTYPE="OUTPUT" PRECISION="50" SCALE="0"/>
    <TRANSFORMFIELD DATATYPE="number" DEFAULTVALUE="" DESCRIPTION="" EXPRESSION="CREDIT_LIMIT" EXPRESSIONTYPE="GENERAL" NAME="CREDIT_LIMIT" PICTURETEXT="" PORTTYPE="INPUT/OUTPUT" PRECISION="15" SCALE="2"/>
    <TRANSFORMFIELD DATATYPE="string" DEFAULTVALUE="" DESCRIPTION="" EXPRESSION="COUNTRY_CODE" EXPRESSIONTYPE="GENERAL" NAME="COUNTRY_CODE" PICTURETEXT="" PORTTYPE="INPUT/OUTPUT" PRECISION="3" SCALE="0"/>
    <TRANSFORMFIELD DATATYPE="date/time" DEFAULTVALUE="" DESCRIPTION="" EXPRESSION="SYSDATE" EXPRESSIONTYPE="GENERAL" NAME="ETL_LOAD_DATE" PICTURETEXT="" PORTTYPE="OUTPUT" PRECISION="19" SCALE="0"/>
  </TRANSFORMATION>

  <!-- Filter: Only active and inactive customers -->
  <TRANSFORMATION DESCRIPTION="Filter out deleted customers" NAME="FIL_ACTIVE_CUSTOMERS" OBJECTVERSION="1" REUSABLE="NO" TYPE="Filter" VERSIONNUMBER="1">
    <TRANSFORMFIELD DATATYPE="number" DEFAULTVALUE="" DESCRIPTION="" NAME="CUSTOMER_ID" PICTURETEXT="" PORTTYPE="INPUT/OUTPUT" PRECISION="10" SCALE="0"/>
    <TRANSFORMFIELD DATATYPE="string" DEFAULTVALUE="" DESCRIPTION="" NAME="FULL_NAME" PICTURETEXT="" PORTTYPE="INPUT/OUTPUT" PRECISION="201" SCALE="0"/>
    <TRANSFORMFIELD DATATYPE="string" DEFAULTVALUE="" DESCRIPTION="" NAME="EMAIL" PICTURETEXT="" PORTTYPE="INPUT/OUTPUT" PRECISION="250" SCALE="0"/>
    <TRANSFORMFIELD DATATYPE="string" DEFAULTVALUE="" DESCRIPTION="" NAME="STATUS_LABEL" PICTURETEXT="" PORTTYPE="INPUT/OUTPUT" PRECISION="50" SCALE="0"/>
    <TRANSFORMFIELD DATATYPE="number" DEFAULTVALUE="" DESCRIPTION="" NAME="CREDIT_LIMIT" PICTURETEXT="" PORTTYPE="INPUT/OUTPUT" PRECISION="15" SCALE="2"/>
    <TRANSFORMFIELD DATATYPE="string" DEFAULTVALUE="" DESCRIPTION="" NAME="COUNTRY_CODE" PICTURETEXT="" PORTTYPE="INPUT/OUTPUT" PRECISION="3" SCALE="0"/>
    <TRANSFORMFIELD DATATYPE="date/time" DEFAULTVALUE="" DESCRIPTION="" NAME="ETL_LOAD_DATE" PICTURETEXT="" PORTTYPE="INPUT/OUTPUT" PRECISION="19" SCALE="0"/>
    <TABLEATTRIBUTE NAME="Filter Condition" VALUE="STATUS_LABEL != 'Unknown'"/>
  </TRANSFORMATION>

  <!-- Connectors: SQ → EXP → FIL → TGT -->
  <CONNECTOR FROMFIELD="CUSTOMER_ID" FROMINSTANCE="SQ_CUSTOMERS" FROMINSTANCETYPE="Source Qualifier" TOFIELD="CUSTOMER_ID" TOINSTANCE="EXP_DERIVE_FIELDS" TOINSTANCETYPE="Expression"/>
  <CONNECTOR FROMFIELD="FIRST_NAME" FROMINSTANCE="SQ_CUSTOMERS" FROMINSTANCETYPE="Source Qualifier" TOFIELD="FIRST_NAME" TOINSTANCE="EXP_DERIVE_FIELDS" TOINSTANCETYPE="Expression"/>
  <CONNECTOR FROMFIELD="LAST_NAME" FROMINSTANCE="SQ_CUSTOMERS" FROMINSTANCETYPE="Source Qualifier" TOFIELD="LAST_NAME" TOINSTANCE="EXP_DERIVE_FIELDS" TOINSTANCETYPE="Expression"/>
  <CONNECTOR FROMFIELD="EMAIL" FROMINSTANCE="SQ_CUSTOMERS" FROMINSTANCETYPE="Source Qualifier" TOFIELD="EMAIL" TOINSTANCE="EXP_DERIVE_FIELDS" TOINSTANCETYPE="Expression"/>
  <CONNECTOR FROMFIELD="STATUS" FROMINSTANCE="SQ_CUSTOMERS" FROMINSTANCETYPE="Source Qualifier" TOFIELD="STATUS" TOINSTANCE="EXP_DERIVE_FIELDS" TOINSTANCETYPE="Expression"/>
  <CONNECTOR FROMFIELD="CREDIT_LIMIT" FROMINSTANCE="SQ_CUSTOMERS" FROMINSTANCETYPE="Source Qualifier" TOFIELD="CREDIT_LIMIT" TOINSTANCE="EXP_DERIVE_FIELDS" TOINSTANCETYPE="Expression"/>
  <CONNECTOR FROMFIELD="COUNTRY_CODE" FROMINSTANCE="SQ_CUSTOMERS" FROMINSTANCETYPE="Source Qualifier" TOFIELD="COUNTRY_CODE" TOINSTANCE="EXP_DERIVE_FIELDS" TOINSTANCETYPE="Expression"/>

  <CONNECTOR FROMFIELD="CUSTOMER_ID" FROMINSTANCE="EXP_DERIVE_FIELDS" FROMINSTANCETYPE="Expression" TOFIELD="CUSTOMER_ID" TOINSTANCE="FIL_ACTIVE_CUSTOMERS" TOINSTANCETYPE="Filter"/>
  <CONNECTOR FROMFIELD="FULL_NAME" FROMINSTANCE="EXP_DERIVE_FIELDS" FROMINSTANCETYPE="Expression" TOFIELD="FULL_NAME" TOINSTANCE="FIL_ACTIVE_CUSTOMERS" TOINSTANCETYPE="Filter"/>
  <CONNECTOR FROMFIELD="EMAIL" FROMINSTANCE="EXP_DERIVE_FIELDS" FROMINSTANCETYPE="Expression" TOFIELD="EMAIL" TOINSTANCE="FIL_ACTIVE_CUSTOMERS" TOINSTANCETYPE="Filter"/>
  <CONNECTOR FROMFIELD="STATUS_LABEL" FROMINSTANCE="EXP_DERIVE_FIELDS" FROMINSTANCETYPE="Expression" TOFIELD="STATUS_LABEL" TOINSTANCE="FIL_ACTIVE_CUSTOMERS" TOINSTANCETYPE="Filter"/>
  <CONNECTOR FROMFIELD="CREDIT_LIMIT" FROMINSTANCE="EXP_DERIVE_FIELDS" FROMINSTANCETYPE="Expression" TOFIELD="CREDIT_LIMIT" TOINSTANCE="FIL_ACTIVE_CUSTOMERS" TOINSTANCETYPE="Filter"/>
  <CONNECTOR FROMFIELD="COUNTRY_CODE" FROMINSTANCE="EXP_DERIVE_FIELDS" FROMINSTANCETYPE="Expression" TOFIELD="COUNTRY_CODE" TOINSTANCE="FIL_ACTIVE_CUSTOMERS" TOINSTANCETYPE="Filter"/>
  <CONNECTOR FROMFIELD="ETL_LOAD_DATE" FROMINSTANCE="EXP_DERIVE_FIELDS" FROMINSTANCETYPE="Expression" TOFIELD="ETL_LOAD_DATE" TOINSTANCE="FIL_ACTIVE_CUSTOMERS" TOINSTANCETYPE="Filter"/>

  <CONNECTOR FROMFIELD="CUSTOMER_ID" FROMINSTANCE="FIL_ACTIVE_CUSTOMERS" FROMINSTANCETYPE="Filter" TOFIELD="CUSTOMER_ID" TOINSTANCE="DIM_CUSTOMER" TOINSTANCETYPE="Target Definition"/>
  <CONNECTOR FROMFIELD="FULL_NAME" FROMINSTANCE="FIL_ACTIVE_CUSTOMERS" FROMINSTANCETYPE="Filter" TOFIELD="FULL_NAME" TOINSTANCE="DIM_CUSTOMER" TOINSTANCETYPE="Target Definition"/>
  <CONNECTOR FROMFIELD="EMAIL" FROMINSTANCE="FIL_ACTIVE_CUSTOMERS" FROMINSTANCETYPE="Filter" TOFIELD="EMAIL" TOINSTANCE="DIM_CUSTOMER" TOINSTANCETYPE="Target Definition"/>
  <CONNECTOR FROMFIELD="STATUS_LABEL" FROMINSTANCE="FIL_ACTIVE_CUSTOMERS" FROMINSTANCETYPE="Filter" TOFIELD="STATUS_LABEL" TOINSTANCE="DIM_CUSTOMER" TOINSTANCETYPE="Target Definition"/>
  <CONNECTOR FROMFIELD="CREDIT_LIMIT" FROMINSTANCE="FIL_ACTIVE_CUSTOMERS" FROMINSTANCETYPE="Filter" TOFIELD="CREDIT_LIMIT" TOINSTANCE="DIM_CUSTOMER" TOINSTANCETYPE="Target Definition"/>
  <CONNECTOR FROMFIELD="COUNTRY_CODE" FROMINSTANCE="FIL_ACTIVE_CUSTOMERS" FROMINSTANCETYPE="Filter" TOFIELD="COUNTRY_CODE" TOINSTANCE="DIM_CUSTOMER" TOINSTANCETYPE="Target Definition"/>
  <CONNECTOR FROMFIELD="ETL_LOAD_DATE" FROMINSTANCE="FIL_ACTIVE_CUSTOMERS" FROMINSTANCETYPE="Filter" TOFIELD="ETL_LOAD_DATE" TOINSTANCE="DIM_CUSTOMER" TOINSTANCETYPE="Target Definition"/>

  <TARGETLOADORDER ORDER="1" TARGETINSTANCE="DIM_CUSTOMER"/>

</MAPPING>

</FOLDER>
</REPOSITORY>
</POWERMART>
